crabtree-0.0.0.dist-info/METADATA
crabtree-0.0.0.dist-info/WHEEL
crabtree/__init__.py
crabtree/crabtree.cpython-310-i386-linux-gnu.so
crabtree-0.0.0.dist-info/RECORD
