Metadata-Version: 2.3
Name: crabtree
Version: 0.0.0
Summary: Add your description here
Requires-Python: >=3.10
